elcuestionario/__init__.py
elcuestionario/app.py
elcuestionario/cli.py
elcuestionario/evaluation.py
elcuestionario/loader.py
elcuestionario/questionnaire.py
elcuestionario/userinput.py
El_Cuestionario-0.5.dist-info/LICENSE
El_Cuestionario-0.5.dist-info/METADATA
El_Cuestionario-0.5.dist-info/WHEEL
El_Cuestionario-0.5.dist-info/entry_points.txt
El_Cuestionario-0.5.dist-info/top_level.txt
El_Cuestionario-0.5.dist-info/RECORD
