Metadata-Version: 2.1
Name: El-Cuestionario
Version: 0.5
Summary: A tiny web application to display and evaluate single-page questionnaires
Home-page: https://homework.nwsnet.de/releases/8909/#el-cuestionario
Author: Jochen Kupperschmidt
Author-email: homework@nwsnet.de
License: GPLv2
Keywords: questionnaire
Platform: any
Classifier: Environment :: Web Environment
Classifier: Framework :: Flask
Classifier: Intended Audience :: Other Audience
Classifier: License :: OSI Approved :: GNU General Public License v2 (GPLv2)
Classifier: Natural Language :: English
Classifier: Operating System :: OS Independent
Classifier: Programming Language :: Python
Classifier: Programming Language :: Python :: 3
Classifier: Programming Language :: Python :: 3.7
Classifier: Programming Language :: Python :: 3.8
Classifier: Programming Language :: Python :: 3.9
Classifier: Topic :: Games/Entertainment
Requires-Python: >=3.7
Requires-Dist: Flask (==1.1.2)
Requires-Dist: Werkzeug (==1.0.1)
